invenio_openaire/__init__.py
invenio_openaire/cli.py
invenio_openaire/config.py
invenio_openaire/errors.py
invenio_openaire/ext.py
invenio_openaire/fetchers.py
invenio_openaire/indexer.py
invenio_openaire/loaders.py
invenio_openaire/minters.py
invenio_openaire/tasks.py
invenio_openaire/version.py
invenio_openaire/data/README.rst
invenio_openaire/data/fundref_registry.rdf.gz
invenio_openaire/data/geonames2countrycodes_iso_3166.txt
invenio_openaire/jsonschemas/__init__.py
invenio_openaire/jsonschemas/funders/funder-v1.0.0.json
invenio_openaire/jsonschemas/grants/grant-v1.0.0.json
invenio_openaire/mappings/__init__.py
invenio_openaire/mappings/funders/funder-v1.0.0.json
invenio_openaire/mappings/grants/grant-v1.0.0.json
invenio_openaire/mappings/v5/__init__.py
invenio_openaire/mappings/v5/funders/funder-v1.0.0.json
invenio_openaire/mappings/v5/grants/grant-v1.0.0.json
invenio_openaire/mappings/v6/__init__.py
invenio_openaire/mappings/v6/funders/funder-v1.0.0.json
invenio_openaire/mappings/v6/grants/grant-v1.0.0.json
invenio_openaire/mappings/v7/__init__.py
invenio_openaire/mappings/v7/funders/funder-v1.0.0.json
invenio_openaire/mappings/v7/grants/grant-v1.0.0.json
invenio_openaire/resolvers/__init__.py
invenio_openaire/resolvers/funders.py
invenio_openaire/resolvers/grants.py
invenio_openaire-1.0.0a16.dist-info/AUTHORS.rst
invenio_openaire-1.0.0a16.dist-info/LICENSE
invenio_openaire-1.0.0a16.dist-info/METADATA
invenio_openaire-1.0.0a16.dist-info/WHEEL
invenio_openaire-1.0.0a16.dist-info/entry_points.txt
invenio_openaire-1.0.0a16.dist-info/top_level.txt
invenio_openaire-1.0.0a16.dist-info/RECORD
