Metadata-Version: 2.1
Name: invenio-openaire
Version: 1.0.0a16
Summary: OpenAIRE service integration for Invenio repositories.
Home-page: https://github.com/inveniosoftware/invenio-openaire
Author: CERN
Author-email: info@inveniosoftware.org
License: MIT
Keywords: invenio openaire
Platform: any
Classifier: Environment :: Web Environment
Classifier: Intended Audience :: Developers
Classifier: License :: OSI Approved :: MIT License
Classifier: Operating System :: OS Independent
Classifier: Programming Language :: Python
Classifier: Topic :: Internet :: WWW/HTTP :: Dynamic Content
Classifier: Topic :: Software Development :: Libraries :: Python Modules
Classifier: Programming Language :: Python :: 2
Classifier: Programming Language :: Python :: 2.7
Classifier: Programming Language :: Python :: 3
Classifier: Programming Language :: Python :: 3.5
Classifier: Programming Language :: Python :: Implementation :: CPython
Classifier: Development Status :: 3 - Alpha
Requires-Dist: Flask (>=0.11.1)
Requires-Dist: Flask-BabelEx (>=0.9.3)
Requires-Dist: Flask-Login (>=0.3.2)
Requires-Dist: invenio-indexer (>=1.1.0)
Requires-Dist: invenio-jsonschemas (>=1.0.0)
Requires-Dist: invenio-pidstore (>=1.0.0)
Requires-Dist: invenio-records-rest (>=1.6.2)
Requires-Dist: invenio-records (>=1.3.0)
Requires-Dist: jsonref (>=0.1)
Requires-Dist: jsonresolver (>=0.2.1)
Requires-Dist: requests (>=2.9.1)
Requires-Dist: sickle (>=0.5.0)
Requires-Dist: six (>=1.11.0)
Provides-Extra: all
Requires-Dist: Sphinx (>=3) ; extra == 'all'
Requires-Dist: invenio-celery (>=1.1.0) ; extra == 'all'
Requires-Dist: invenio-db (>=1.0.1) ; extra == 'all'
Requires-Dist: jsonschema (>=2.5.1) ; extra == 'all'
Requires-Dist: mock (>=1.3.0) ; extra == 'all'
Requires-Dist: pytest-invenio (>=1.4.0) ; extra == 'all'
Provides-Extra: docs
Requires-Dist: Sphinx (>=3) ; extra == 'docs'
Provides-Extra: elasticsearch2
Requires-Dist: invenio-search[elasticsearch2] (>=1.2.0) ; extra == 'elasticsearch2'
Provides-Extra: elasticsearch5
Requires-Dist: invenio-search[elasticsearch5] (>=1.2.0) ; extra == 'elasticsearch5'
Provides-Extra: elasticsearch6
Requires-Dist: invenio-search[elasticsearch6] (>=1.2.0) ; extra == 'elasticsearch6'
Provides-Extra: elasticsearch7
Requires-Dist: invenio-search[elasticsearch7] (>=1.2.0) ; extra == 'elasticsearch7'
Provides-Extra: tests
Requires-Dist: invenio-celery (>=1.1.0) ; extra == 'tests'
Requires-Dist: invenio-db (>=1.0.1) ; extra == 'tests'
Requires-Dist: jsonschema (>=2.5.1) ; extra == 'tests'
Requires-Dist: mock (>=1.3.0) ; extra == 'tests'
Requires-Dist: pytest-invenio (>=1.4.0) ; extra == 'tests'
